{
  "weather": {
    "cur_temp": 24.08,
    "cur_icon": "04d",
    "cur_descr": "пасмурно",
    "last_upd": "22.07.2026 17:07:07",
    "day_name_1": "Чт.",
    "temp_1": "+24",
    "icon_1": "02d",
    "descr_1": "небольшая облачность",
    "day_name_2": "Пт.",
    "temp_2": "+28",
    "icon_2": "02d",
    "descr_2": "небольшая облачность",
    "day_name_3": "Сб.",
    "temp_3": "+32",
    "icon_3": "01d",
    "descr_3": "ясно"
  },
  "namaz": {
    "Фаджр": "03:23",
    "Восход": "05:55",
    "Зухр": "13:42",
    "Аср": "17:53",
    "Магриб": "21:28",
    "Иша": "23:52",
    "last_upd": "22.07.2026 17:07:08"
  },
  "currency_rates": {
    "USD": {
      "buy": 466.0,
      "sale": 470.0
    },
    "EUR": {
      "buy": 529.92,
      "sale": 535.92
    },
    "last_upd": "22.07.2026 17:07:11"
  },
  "temp_history": [
    {
      "temp": 22.54,
      "icon": "04d",
      "descr": "облачно с прояснениями",
      "timestamp": "20.07.2026 20:08:04",
      "index": 1
    },
    {
      "temp": 17.7,
      "icon": "04n",
      "descr": "пасмурно",
      "timestamp": "20.07.2026 22:24:06",
      "index": 2
    },
    {
      "temp": 13.28,
      "icon": "03d",
      "descr": "переменная облачность",
      "timestamp": "21.07.2026 07:24:37",
      "index": 3
    },
    {
      "temp": 22.57,
      "icon": "01d",
      "descr": "ясно",
      "timestamp": "21.07.2026 13:49:40",
      "index": 4
    },
    {
      "temp": 25.19,
      "icon": "01d",
      "descr": "ясно",
      "timestamp": "21.07.2026 17:06:05",
      "index": 5
    },
    {
      "temp": 25.19,
      "icon": "02d",
      "descr": "небольшая облачность",
      "timestamp": "21.07.2026 19:25:03",
      "index": 6
    },
    {
      "temp": 20.17,
      "icon": "01n",
      "descr": "ясно",
      "timestamp": "21.07.2026 22:20:02",
      "index": 7
    },
    {
      "temp": 15.19,
      "icon": "01d",
      "descr": "ясно",
      "timestamp": "22.07.2026 07:23:12",
      "index": 8
    },
    {
      "temp": 22.91,
      "icon": "04d",
      "descr": "облачно с прояснениями",
      "timestamp": "22.07.2026 13:50:03",
      "index": 9
    },
    {
      "temp": 24.08,
      "icon": "04d",
      "descr": "пасмурно",
      "timestamp": "22.07.2026 17:07:07",
      "index": 10
    }
  ],
  "currency_history": [
    {
      "timestamp": "20.07.2026 20:08:08",
      "rates": {
        "USD": {
          "buy": 469.0,
          "sale": 473.0
        },
        "EUR": {
          "buy": 534.75,
          "sale": 540.75
        }
      },
      "index": 1
    },
    {
      "timestamp": "20.07.2026 22:24:09",
      "rates": {
        "USD": {
          "buy": 469.0,
          "sale": 473.0
        },
        "EUR": {
          "buy": 534.75,
          "sale": 540.75
        }
      },
      "index": 2
    },
    {
      "timestamp": "21.07.2026 07:24:41",
      "rates": {
        "USD": {
          "buy": 469.5,
          "sale": 472.5
        },
        "EUR": {
          "buy": 535.25,
          "sale": 540.25
        }
      },
      "index": 3
    },
    {
      "timestamp": "21.07.2026 13:49:44",
      "rates": {
        "USD": {
          "buy": 467.0,
          "sale": 470.0
        },
        "EUR": {
          "buy": 531.46,
          "sale": 536.46
        }
      },
      "index": 4
    },
    {
      "timestamp": "21.07.2026 17:06:08",
      "rates": {
        "USD": {
          "buy": 466.5,
          "sale": 470.0
        },
        "EUR": {
          "buy": 530.96,
          "sale": 536.96
        }
      },
      "index": 5
    },
    {
      "timestamp": "21.07.2026 19:25:08",
      "rates": {
        "USD": {
          "buy": 466.5,
          "sale": 470.0
        },
        "EUR": {
          "buy": 530.96,
          "sale": 536.96
        }
      },
      "index": 6
    },
    {
      "timestamp": "21.07.2026 22:20:06",
      "rates": {
        "USD": {
          "buy": 466.5,
          "sale": 470.0
        },
        "EUR": {
          "buy": 530.96,
          "sale": 536.96
        }
      },
      "index": 7
    },
    {
      "timestamp": "22.07.2026 07:23:16",
      "rates": {
        "USD": {
          "buy": 467.0,
          "sale": 470.0
        },
        "EUR": {
          "buy": 531.46,
          "sale": 536.46
        }
      },
      "index": 8
    },
    {
      "timestamp": "22.07.2026 13:50:06",
      "rates": {
        "USD": {
          "buy": 467.0,
          "sale": 470.0
        },
        "EUR": {
          "buy": 530.99,
          "sale": 535.99
        }
      },
      "index": 9
    },
    {
      "timestamp": "22.07.2026 17:07:11",
      "rates": {
        "USD": {
          "buy": 466.0,
          "sale": 470.0
        },
        "EUR": {
          "buy": 529.92,
          "sale": 535.92
        }
      },
      "index": 10
    }
  ]
}