{
  "weather": {
    "cur_temp": 31.52,
    "cur_icon": "01d",
    "cur_descr": "ясно",
    "last_upd": "27.05.2026 14:55:26",
    "day_name_1": "Чт.",
    "temp_1": "+26",
    "icon_1": "01d",
    "descr_1": "ясно",
    "day_name_2": "Пт.",
    "temp_2": "+28",
    "icon_2": "03d",
    "descr_2": "переменная облачность",
    "day_name_3": "Сб.",
    "temp_3": "+29",
    "icon_3": "04d",
    "descr_3": "облачно с прояснениями"
  },
  "namaz": {
    "Фаджр": "03:11",
    "Восход": "05:39",
    "Зухр": "13:32",
    "Аср": "17:46",
    "Магриб": "21:26",
    "Иша": "23:46",
    "last_upd": "27.05.2026 14:55:27"
  },
  "currency_rates": {
    "EUR": {
      "buy": 555.72,
      "sale": 560.72
    },
    "USD": {
      "buy": 477.5,
      "sale": 481.5
    },
    "last_upd": "27.05.2026 14:55:30"
  },
  "temp_history": [
    {
      "temp": 23.54,
      "icon": "01n",
      "descr": "ясно",
      "timestamp": "24.05.2026 22:09:10",
      "index": 1
    },
    {
      "temp": 20.29,
      "icon": "01d",
      "descr": "ясно",
      "timestamp": "25.05.2026 08:39:46",
      "index": 2
    },
    {
      "temp": 31.5,
      "icon": "01d",
      "descr": "ясно",
      "timestamp": "25.05.2026 15:31:29",
      "index": 3
    },
    {
      "temp": 29.55,
      "icon": "01d",
      "descr": "ясно",
      "timestamp": "25.05.2026 19:47:29",
      "index": 4
    },
    {
      "temp": 22.5,
      "icon": "01n",
      "descr": "ясно",
      "timestamp": "25.05.2026 22:23:05",
      "index": 5
    },
    {
      "temp": 18.95,
      "icon": "01d",
      "descr": "ясно",
      "timestamp": "26.05.2026 08:11:04",
      "index": 6
    },
    {
      "temp": 32.49,
      "icon": "01d",
      "descr": "ясно",
      "timestamp": "26.05.2026 18:45:09",
      "index": 7
    },
    {
      "temp": 22.53,
      "icon": "01n",
      "descr": "ясно",
      "timestamp": "26.05.2026 22:56:40",
      "index": 8
    },
    {
      "temp": 19.51,
      "icon": "01d",
      "descr": "ясно",
      "timestamp": "27.05.2026 08:24:57",
      "index": 9
    },
    {
      "temp": 31.52,
      "icon": "01d",
      "descr": "ясно",
      "timestamp": "27.05.2026 14:55:26",
      "index": 10
    }
  ],
  "currency_history": [
    {
      "timestamp": "24.05.2026 22:09:13",
      "rates": {
        "USD": {
          "buy": 471.0,
          "sale": 474.5
        },
        "EUR": {
          "buy": 545.18,
          "sale": 551.18
        }
      },
      "index": 1
    },
    {
      "timestamp": "25.05.2026 08:39:51",
      "rates": {
        "USD": {
          "buy": 470.5,
          "sale": 473.5
        },
        "EUR": {
          "buy": 546.41,
          "sale": 551.41
        }
      },
      "index": 2
    },
    {
      "timestamp": "25.05.2026 15:31:32",
      "rates": {
        "USD": {
          "buy": 471.5,
          "sale": 474.5
        },
        "EUR": {
          "buy": 547.57,
          "sale": 552.57
        }
      },
      "index": 3
    },
    {
      "timestamp": "25.05.2026 19:47:32",
      "rates": {
        "USD": {
          "buy": 471.0,
          "sale": 475.0
        },
        "EUR": {
          "buy": 547.07,
          "sale": 553.07
        }
      },
      "index": 4
    },
    {
      "timestamp": "25.05.2026 22:23:08",
      "rates": {
        "USD": {
          "buy": 471.0,
          "sale": 475.0
        },
        "EUR": {
          "buy": 547.07,
          "sale": 553.07
        }
      },
      "index": 5
    },
    {
      "timestamp": "26.05.2026 08:11:06",
      "rates": {
        "USD": {
          "buy": 474.0,
          "sale": 477.5
        },
        "EUR": {
          "buy": 550.59,
          "sale": 555.59
        }
      },
      "index": 6
    },
    {
      "timestamp": "26.05.2026 18:45:13",
      "rates": {
        "USD": {
          "buy": 477.0,
          "sale": 482.0
        },
        "EUR": {
          "buy": 555.22,
          "sale": 561.22
        }
      },
      "index": 7
    },
    {
      "timestamp": "26.05.2026 22:56:43",
      "rates": {
        "USD": {
          "buy": 477.0,
          "sale": 482.0
        },
        "EUR": {
          "buy": 555.22,
          "sale": 561.22
        }
      },
      "index": 8
    },
    {
      "timestamp": "27.05.2026 08:25:02",
      "rates": {
        "USD": {
          "buy": 477.5,
          "sale": 481.5
        },
        "EUR": {
          "buy": 555.72,
          "sale": 560.72
        }
      },
      "index": 9
    },
    {
      "timestamp": "27.05.2026 14:55:30",
      "rates": {
        "USD": {
          "buy": 477.5,
          "sale": 481.5
        },
        "EUR": {
          "buy": 555.72,
          "sale": 560.72
        }
      },
      "index": 10
    }
  ]
}