{
  "weather": {
    "cur_temp": 8.46,
    "cur_icon": "01d",
    "cur_descr": "ясно",
    "last_upd": "30.04.2026 07:33:52",
    "day_name_1": "Пт.",
    "temp_1": "+18",
    "icon_1": "01d",
    "descr_1": "ясно",
    "day_name_2": "Сб.",
    "temp_2": "+22",
    "icon_2": "10d",
    "descr_2": "небольшой дождь",
    "day_name_3": "Вс.",
    "temp_3": "+18",
    "icon_3": "04d",
    "descr_3": "пасмурно"
  },
  "namaz": {
    "Фаджр": "04:03",
    "Восход": "06:16",
    "Зухр": "13:33",
    "Аср": "17:31",
    "Магриб": "20:50",
    "Иша": "22:54",
    "last_upd": "30.04.2026 07:33:53"
  },
  "currency_rates": {
    "EUR": {
      "buy": 538.71,
      "sale": 543.71
    },
    "USD": {
      "buy": 461.5,
      "sale": 464.5
    },
    "last_upd": "30.04.2026 07:34:04"
  },
  "temp_history": [
    {
      "temp": 21.27,
      "icon": "01d",
      "descr": "ясно",
      "timestamp": "28.04.2026 13:49:10",
      "index": 1
    },
    {
      "temp": 23.52,
      "icon": "01d",
      "descr": "ясно",
      "timestamp": "28.04.2026 17:29:12",
      "index": 2
    },
    {
      "temp": 20.55,
      "icon": "01d",
      "descr": "ясно",
      "timestamp": "28.04.2026 19:49:59",
      "index": 3
    },
    {
      "temp": 15.74,
      "icon": "01n",
      "descr": "ясно",
      "timestamp": "28.04.2026 22:20:25",
      "index": 4
    },
    {
      "temp": 8.91,
      "icon": "01d",
      "descr": "ясно",
      "timestamp": "29.04.2026 07:30:01",
      "index": 5
    },
    {
      "temp": 20.21,
      "icon": "01d",
      "descr": "ясно",
      "timestamp": "29.04.2026 13:41:47",
      "index": 6
    },
    {
      "temp": 21.55,
      "icon": "01d",
      "descr": "ясно",
      "timestamp": "29.04.2026 17:19:57",
      "index": 7
    },
    {
      "temp": 19.55,
      "icon": "01d",
      "descr": "ясно",
      "timestamp": "29.04.2026 19:42:31",
      "index": 8
    },
    {
      "temp": 14.56,
      "icon": "01n",
      "descr": "ясно",
      "timestamp": "29.04.2026 22:13:04",
      "index": 9
    },
    {
      "temp": 8.46,
      "icon": "01d",
      "descr": "ясно",
      "timestamp": "30.04.2026 07:33:52",
      "index": 10
    }
  ],
  "currency_history": [
    {
      "timestamp": "28.04.2026 13:49:14",
      "rates": {
        "USD": {
          "buy": 457.0,
          "sale": 460.0
        },
        "EUR": {
          "buy": 533.45,
          "sale": 538.45
        }
      },
      "index": 1
    },
    {
      "timestamp": "28.04.2026 17:29:21",
      "rates": {
        "USD": {
          "buy": 457.0,
          "sale": 460.5
        },
        "EUR": {
          "buy": 532.95,
          "sale": 538.95
        }
      },
      "index": 2
    },
    {
      "timestamp": "28.04.2026 19:50:14",
      "rates": {
        "USD": {
          "buy": 457.0,
          "sale": 460.5
        },
        "EUR": {
          "buy": 532.95,
          "sale": 538.95
        }
      },
      "index": 3
    },
    {
      "timestamp": "28.04.2026 22:20:28",
      "rates": {
        "USD": {
          "buy": 457.0,
          "sale": 460.5
        },
        "EUR": {
          "buy": 532.95,
          "sale": 538.95
        }
      },
      "index": 4
    },
    {
      "timestamp": "29.04.2026 07:30:04",
      "rates": {
        "USD": {
          "buy": 457.0,
          "sale": 460.0
        },
        "EUR": {
          "buy": 533.45,
          "sale": 538.45
        }
      },
      "index": 5
    },
    {
      "timestamp": "29.04.2026 13:41:54",
      "rates": {
        "USD": {
          "buy": 461.5,
          "sale": 464.5
        },
        "EUR": {
          "buy": 538.71,
          "sale": 543.71
        }
      },
      "index": 6
    },
    {
      "timestamp": "29.04.2026 17:20:01",
      "rates": {
        "USD": {
          "buy": 461.5,
          "sale": 465.0
        },
        "EUR": {
          "buy": 538.21,
          "sale": 544.21
        }
      },
      "index": 7
    },
    {
      "timestamp": "29.04.2026 19:42:36",
      "rates": {
        "USD": {
          "buy": 461.5,
          "sale": 465.0
        },
        "EUR": {
          "buy": 538.21,
          "sale": 544.21
        }
      },
      "index": 8
    },
    {
      "timestamp": "29.04.2026 22:13:07",
      "rates": {
        "USD": {
          "buy": 461.5,
          "sale": 465.0
        },
        "EUR": {
          "buy": 538.21,
          "sale": 544.21
        }
      },
      "index": 9
    },
    {
      "timestamp": "30.04.2026 07:34:04",
      "rates": {
        "USD": {
          "buy": 461.5,
          "sale": 464.5
        },
        "EUR": {
          "buy": 538.71,
          "sale": 543.71
        }
      },
      "index": 10
    }
  ]
}